semantic_chunker/__init__.py
semantic_chunker-0.2.0.dist-info/METADATA
semantic_chunker-0.2.0.dist-info/WHEEL
semantic_chunker-0.2.0.dist-info/licenses/LICENSE
semantic_chunker-0.2.0.dist-info/RECORD
