Metadata-Version: 2.4
Name: semantic-chunker
Version: 0.2.0
Summary: Semantic Chunker
Project-URL: Repository, https://github.com/Goldziher/semantic-chunker
Author-email: Na'aman Hirschfeld <nhirschfeld@gmail.com>
License: MIT
License-File: LICENSE
Keywords: ai,chunking,code-splitter,semantic,semantic-chunking,text-splitter,tree-sitter
Classifier: Development Status :: 4 - Beta
Classifier: Intended Audience :: Information Technology
Classifier: Natural Language :: English
Classifier: Operating System :: OS Independent
Classifier: Programming Language :: Python
Classifier: Programming Language :: Python :: 3 :: Only
Classifier: Programming Language :: Python :: 3.9
Classifier: Programming Language :: Python :: 3.10
Classifier: Programming Language :: Python :: 3.11
Classifier: Programming Language :: Python :: 3.12
Classifier: Programming Language :: Python :: 3.13
Classifier: Topic :: Software Development
Classifier: Topic :: Software Development :: Libraries
Classifier: Topic :: Software Development :: Libraries :: Python Modules
Classifier: Typing :: Typed
Requires-Python: >=3.9
Requires-Dist: semantic-text-splitter>=0.22.0
Requires-Dist: typing-extensions>=4.12.2
Provides-Extra: all
Requires-Dist: tokenizers>=0.21.0; extra == 'all'
Requires-Dist: tree-sitter-language-pack>=0.4.0; extra == 'all'
Provides-Extra: code
Requires-Dist: tree-sitter-language-pack>=0.4.0; extra == 'code'
Provides-Extra: tokenizers
Requires-Dist: tokenizers>=0.21.0; extra == 'tokenizers'
